.gitignore
.gitlab-ci.yml
CHANGELOG.md
LICENSE.txt
MATERIAL_ICONS_USAGE.md
PKG-INFO
README.md
pyproject.toml
.github/workflows/semantic_release.yml
bec_qthemes/__init__.py
bec_qthemes/_cache.py
bec_qthemes/_color.py
bec_qthemes/_main.py
bec_qthemes/_theme.py
bec_qthemes/_util.py
bec_qthemes/_icon/__init__.py
bec_qthemes/_icon/icon_engine.py
bec_qthemes/_icon/material_icons.py
bec_qthemes/_icon/svg_util.py
bec_qthemes/_template/__init__.py
bec_qthemes/_template/engine.py
bec_qthemes/_template/filter.py
bec_qthemes/qss_editor/__init__.py
bec_qthemes/qss_editor/qss_editor.py
bec_qthemes/qss_editor/theme_ads.qss
bec_qthemes/qss_editor/theme_base.qss
bec_qthemes/qss_editor/qss/theme_base.qss
bec_qthemes/qss_editor/themes/dark.xml
bec_qthemes/qss_editor/themes/light.xml
bec_qthemes/qss_editor/themes_old/dark.xml
bec_qthemes/qss_editor/themes_old/dark_copilot.xml
bec_qthemes/qss_editor/themes_old/dark_github.xml
bec_qthemes/qss_editor/themes_old/dark_gpt.xml
bec_qthemes/qss_editor/themes_old/dark_jetbrains.xml
bec_qthemes/qss_editor/themes_old/jet_coolors.xml
bec_qthemes/qss_editor/themes_old/jetbrains_dark_tuned.xml
bec_qthemes/qss_editor/themes_old/jetbrains_dark_tuned_more.xml
bec_qthemes/qss_editor/themes_old/jetbrains_dark_tuned_more_more.xml
bec_qthemes/qss_editor/themes_old/jetbrains_dark_tuned_more_with_card.xml
bec_qthemes/qss_editor/themes_old/light.xml
bec_qthemes/qss_editor/themes_old/light_gpt.xml
bec_qthemes/qss_editor/themes_old/light_jetbrains.xml
examples/__init__.py
examples/example.py
style/svg/all_material_icons.json
style/svg/all_material_icons_filled.json
tests/test_cache.py
tests/test_color.py
tests/test_loading.py
tests/test_qdarktheme.py
tests/test_qdarktheme_with_qt.py
tests/test_svg.py
tests/test_template_engine.py
tests/test_util.py
tools/__init__.py
tools/_util.py
tools/material_icons.py
bec_qthemes-1.2.2.dist-info/METADATA
bec_qthemes-1.2.2.dist-info/WHEEL
bec_qthemes-1.2.2.dist-info/licenses/LICENSE.txt
bec_qthemes-1.2.2.dist-info/RECORD
