Metadata-Version: 2.4
Name: bec_qthemes
Version: 1.2.2
Summary: BEC Qt themes
Project-URL: Bug Tracker, https://github.com/bec-project/bec_qthemes/issues
Project-URL: Homepage, https://github.com/bec-project/bec_qthemes
Project-URL: changelog, https://github.com/bec-project/bec_qthemes/blob/main/CHANGELOG.md
License-File: LICENSE.txt
Classifier: Development Status :: 3 - Alpha
Classifier: Programming Language :: Python :: 3
Classifier: Topic :: Scientific/Engineering
Requires-Python: >=3.10
Requires-Dist: qtpy~=2.4
Provides-Extra: dev
Requires-Dist: black~=24.0; extra == 'dev'
Requires-Dist: coverage~=7.0; extra == 'dev'
Requires-Dist: isort>=5.13.2,~=5.13; extra == 'dev'
Requires-Dist: pylint~=3.0; extra == 'dev'
Requires-Dist: pytest-qt~=4.4; extra == 'dev'
Requires-Dist: pytest-random-order~=1.1; extra == 'dev'
